pdf_processing_florence/__init__.py
pdf_processing_florence/apply_florence.py
pdf_processing_florence/convert.py
pdf_processing_florence/extract_text.py
pdf_processing_florence-0.1.0.dist-info/LICENSE
pdf_processing_florence-0.1.0.dist-info/METADATA
pdf_processing_florence-0.1.0.dist-info/WHEEL
pdf_processing_florence-0.1.0.dist-info/top_level.txt
pdf_processing_florence-0.1.0.dist-info/RECORD
