Metadata-Version: 2.1
Name: pdf_processing_florence
Version: 0.1.0
Summary: A library for processing PDFs with Florence
Home-page: https://github.com/yourusername/pdf_processing_florence
Author: Carlos Rosas
Author-email: carlos@pleias.com
Classifier: Programming Language :: Python :: 3
Classifier: License :: OSI Approved :: MIT License
Classifier: Operating System :: OS Independent
Requires-Python: >=3.6
License-File: LICENSE
Requires-Dist: pdf2image
Requires-Dist: Pillow
Requires-Dist: torch
Requires-Dist: transformers
Requires-Dist: PyMuPDF
